cdptools/__init__.py
cdptools/cdp_instance.py
cdptools/configs.py
cdptools/audio_splitters/__init__.py
cdptools/audio_splitters/audio_splitter.py
cdptools/audio_splitters/ffmpeg_audio_splitter.py
cdptools/bin/__init__.py
cdptools/bin/clone_db.py
cdptools/bin/clone_file_store.py
cdptools/bin/process_single_event.py
cdptools/bin/run_cdp_pipeline.py
cdptools/databases/__init__.py
cdptools/databases/cloud_firestore_database.py
cdptools/databases/database.py
cdptools/databases/exceptions.py
cdptools/dev_utils/__init__.py
cdptools/dev_utils/load_custom_object.py
cdptools/dev_utils/run_manager.py
cdptools/event_scrapers/__init__.py
cdptools/event_scrapers/event_scraper.py
cdptools/event_scrapers/exceptions.py
cdptools/event_scrapers/seattle_event_scraper.py
cdptools/file_stores/__init__.py
cdptools/file_stores/app_dirs_file_store.py
cdptools/file_stores/exceptions.py
cdptools/file_stores/file_store.py
cdptools/file_stores/gcs_file_store.py
cdptools/indexers/__init__.py
cdptools/indexers/exceptions.py
cdptools/indexers/indexer.py
cdptools/indexers/tfidf_indexer.py
cdptools/legistar_utils/__init__.py
cdptools/legistar_utils/events.py
cdptools/pipelines/__init__.py
cdptools/pipelines/event_gather_pipeline.py
cdptools/pipelines/event_index_pipeline.py
cdptools/pipelines/minutes_item_index_pipeline.py
cdptools/pipelines/pipeline.py
cdptools/research_utils/__init__.py
cdptools/research_utils/transcripts.py
cdptools/sr_models/__init__.py
cdptools/sr_models/constants.py
cdptools/sr_models/google_cloud_sr_model.py
cdptools/sr_models/sr_model.py
cdptools/sr_models/webvtt_sr_model.py
cdptools-2.0.6.dist-info/LICENSE
cdptools-2.0.6.dist-info/METADATA
cdptools-2.0.6.dist-info/WHEEL
cdptools-2.0.6.dist-info/entry_points.txt
cdptools-2.0.6.dist-info/top_level.txt
cdptools-2.0.6.dist-info/RECORD
