Metadata-Version: 2.1
Name: cdptools
Version: 2.0.6
Summary: Tools to interact with and deploy CouncilDataProject instances
Home-page: https://github.com/CouncilDataProject/cdptools
Author: Jackson Maxfield Brown, Nicholas Weber
Author-email: jmaxfieldbrown@gmail.com, nmweber@uw.edu
License: BSD-3-Clause
Platform: UNKNOWN
Classifier: Development Status :: 5 - Production/Stable
Classifier: Intended Audience :: Developers
Classifier: Intended Audience :: Science/Research
Classifier: License :: OSI Approved :: BSD License
Classifier: Natural Language :: English
Classifier: Programming Language :: Python :: 3.6
Classifier: Programming Language :: Python :: 3.7
Classifier: Topic :: Utilities
Requires-Dist: beautifulsoup4 (>=4.9.1)
Requires-Dist: ffmpeg-python (>=0.2.0)
Requires-Dist: rapidfuzz (>=0.9.1)
Requires-Dist: nltk (>=3.5)
Requires-Dist: pandas (>=1.0.4)
Requires-Dist: requests[security] (>=2.23.0)
Requires-Dist: schedule (>=0.6.0)
Requires-Dist: setuptools (>=44.0.0)
Requires-Dist: six (>=1.14.0)
Requires-Dist: tika (>=1.24)
Requires-Dist: webvtt-py (>=0.4.5)
Requires-Dist: truecase (>=0.0.9)
Provides-Extra: all
Requires-Dist: beautifulsoup4 (>=4.9.1) ; extra == 'all'
Requires-Dist: ffmpeg-python (>=0.2.0) ; extra == 'all'
Requires-Dist: rapidfuzz (>=0.9.1) ; extra == 'all'
Requires-Dist: nltk (>=3.5) ; extra == 'all'
Requires-Dist: pandas (>=1.0.4) ; extra == 'all'
Requires-Dist: requests[security] (>=2.23.0) ; extra == 'all'
Requires-Dist: schedule (>=0.6.0) ; extra == 'all'
Requires-Dist: setuptools (>=44.0.0) ; extra == 'all'
Requires-Dist: six (>=1.14.0) ; extra == 'all'
Requires-Dist: tika (>=1.24) ; extra == 'all'
Requires-Dist: webvtt-py (>=0.4.5) ; extra == 'all'
Requires-Dist: truecase (>=0.0.9) ; extra == 'all'
Requires-Dist: appdirs (>=1.4.3) ; extra == 'all'
Requires-Dist: cryptography (>=2.9.2) ; extra == 'all'
Requires-Dist: firebase-admin (==4.3.0) ; extra == 'all'
Requires-Dist: google-api-core[grpc] (==1.22.1) ; extra == 'all'
Requires-Dist: google-api-python-client (==1.10.0) ; extra == 'all'
Requires-Dist: google-auth (==1.20.1) ; extra == 'all'
Requires-Dist: google-cloud-core (==1.4.1) ; extra == 'all'
Requires-Dist: google-cloud-firestore (==1.8.1) ; extra == 'all'
Requires-Dist: google-cloud-speech (==1.3.2) ; extra == 'all'
Requires-Dist: google-cloud-storage (==1.30.0) ; extra == 'all'
Requires-Dist: google-resumable-media (==0.7.1) ; extra == 'all'
Requires-Dist: black (>=19.10b0) ; extra == 'all'
Requires-Dist: codecov (>=2.1.4) ; extra == 'all'
Requires-Dist: flake8 (>=3.8.3) ; extra == 'all'
Requires-Dist: flake8-debugger (>=3.2.1) ; extra == 'all'
Requires-Dist: pytest (>=5.4.3) ; extra == 'all'
Requires-Dist: pytest-cov (>=2.9.0) ; extra == 'all'
Requires-Dist: pytest-raises (>=0.11) ; extra == 'all'
Requires-Dist: pytest-runner (>=5.2) ; extra == 'all'
Requires-Dist: bumpversion (>=0.6.0) ; extra == 'all'
Requires-Dist: coverage (>=5.1) ; extra == 'all'
Requires-Dist: gitchangelog (>=3.0.4) ; extra == 'all'
Requires-Dist: ipython (>=7.15.0) ; extra == 'all'
Requires-Dist: m2r (>=0.2.1) ; extra == 'all'
Requires-Dist: Sphinx (<3,>=2.0.0b1) ; extra == 'all'
Requires-Dist: sphinx-rtd-theme (>=0.4.3) ; extra == 'all'
Requires-Dist: tox (>=3.15.2) ; extra == 'all'
Requires-Dist: twine (>=3.1.1) ; extra == 'all'
Requires-Dist: wheel (>=0.34.2) ; extra == 'all'
Provides-Extra: dev
Requires-Dist: pytest-runner (>=5.2) ; extra == 'dev'
Requires-Dist: black (>=19.10b0) ; extra == 'dev'
Requires-Dist: codecov (>=2.1.4) ; extra == 'dev'
Requires-Dist: flake8 (>=3.8.3) ; extra == 'dev'
Requires-Dist: flake8-debugger (>=3.2.1) ; extra == 'dev'
Requires-Dist: pytest (>=5.4.3) ; extra == 'dev'
Requires-Dist: pytest-cov (>=2.9.0) ; extra == 'dev'
Requires-Dist: pytest-raises (>=0.11) ; extra == 'dev'
Requires-Dist: bumpversion (>=0.6.0) ; extra == 'dev'
Requires-Dist: coverage (>=5.1) ; extra == 'dev'
Requires-Dist: gitchangelog (>=3.0.4) ; extra == 'dev'
Requires-Dist: ipython (>=7.15.0) ; extra == 'dev'
Requires-Dist: m2r (>=0.2.1) ; extra == 'dev'
Requires-Dist: Sphinx (<3,>=2.0.0b1) ; extra == 'dev'
Requires-Dist: sphinx-rtd-theme (>=0.4.3) ; extra == 'dev'
Requires-Dist: tox (>=3.15.2) ; extra == 'dev'
Requires-Dist: twine (>=3.1.1) ; extra == 'dev'
Requires-Dist: wheel (>=0.34.2) ; extra == 'dev'
Provides-Extra: extras
Requires-Dist: appdirs (>=1.4.3) ; extra == 'extras'
Provides-Extra: seattle
Requires-Dist: cryptography (>=2.9.2) ; extra == 'seattle'
Requires-Dist: firebase-admin (==4.3.0) ; extra == 'seattle'
Requires-Dist: google-api-core[grpc] (==1.22.1) ; extra == 'seattle'
Requires-Dist: google-api-python-client (==1.10.0) ; extra == 'seattle'
Requires-Dist: google-auth (==1.20.1) ; extra == 'seattle'
Requires-Dist: google-cloud-core (==1.4.1) ; extra == 'seattle'
Requires-Dist: google-cloud-firestore (==1.8.1) ; extra == 'seattle'
Requires-Dist: google-cloud-speech (==1.3.2) ; extra == 'seattle'
Requires-Dist: google-cloud-storage (==1.30.0) ; extra == 'seattle'
Requires-Dist: google-resumable-media (==0.7.1) ; extra == 'seattle'
Provides-Extra: setup
Requires-Dist: pytest-runner (>=5.2) ; extra == 'setup'
Provides-Extra: test
Requires-Dist: black (>=19.10b0) ; extra == 'test'
Requires-Dist: codecov (>=2.1.4) ; extra == 'test'
Requires-Dist: flake8 (>=3.8.3) ; extra == 'test'
Requires-Dist: flake8-debugger (>=3.2.1) ; extra == 'test'
Requires-Dist: pytest (>=5.4.3) ; extra == 'test'
Requires-Dist: pytest-cov (>=2.9.0) ; extra == 'test'
Requires-Dist: pytest-raises (>=0.11) ; extra == 'test'
